secret_word_selector-1.0.0.data/scripts/sws
swsm/__init__.py
swsm/auxi.py
swsm/cmd_opts.py
swsm/conf.py
swsm/exception_msgs.py
swsm/security.py
secret_word_selector-1.0.0.dist-info/LICENSE
secret_word_selector-1.0.0.dist-info/METADATA
secret_word_selector-1.0.0.dist-info/WHEEL
secret_word_selector-1.0.0.dist-info/top_level.txt
secret_word_selector-1.0.0.dist-info/RECORD
