Metadata-Version: 2.1
Name: secret-word-selector
Version: 1.0.0
Summary: Select the characters at specified indices of your secret word
Home-page: https://github.com/casene/sws---Secret-Word-Selector
Author: Casene
Author-email: casene@protonmail.com
License: UNKNOWN
Platform: UNKNOWN
Classifier: Environment :: Console
Classifier: Topic :: Utilities
Classifier: Programming Language :: Python :: 3
Classifier: License :: OSI Approved :: GNU General Public License v3 (GPLv3)
Classifier: Operating System :: OS Independent
Requires-Python: >=3.6
License-File: LICENSE
Requires-Dist: cryptography
